pyticc/__init__.py
pyticc/base.py
pyticc/cc1101.py
pyticc/utils.py
pyticc-0.0.5.dist-info/LICENSE
pyticc-0.0.5.dist-info/METADATA
pyticc-0.0.5.dist-info/WHEEL
pyticc-0.0.5.dist-info/top_level.txt
pyticc-0.0.5.dist-info/RECORD
