Metadata-Version: 2.1
Name: pyticc
Version: 0.0.5
Summary: Python module to interface with Texas Instruments CCx Sub-1Ghz RF transceivers over SPI.
Home-page: https://github.com/jeffleary00/pyticc
Author: Jeff Leary
Author-email: sillymonkeysoftware@gmail.com
License: UNKNOWN
Platform: UNKNOWN
Requires-Dist: spidev
